{
  "captured_at": "2026-05-28T02:26:40.150713+00:00",
  "elapsed_ms": 238.3,
  "outcome": "fail-400-P1-va-create-REVIEW-business",
  "request": {
    "method": "POST",
    "url": "https://api.balampay.com/v1/virtual-accounts",
    "headers": {
      "Content-Type": "application/json",
      "x-api-key": "REDACTED(40)",
      "Authorization": "REDACTED(872)",
      "idempotency-key": "a765a99e-6639-4fdd-83da-d82ec2d52144"
    },
    "body": {
      "user_id": "0ba8a87a-a49e-423b-86fb-c6a025ba27f9",
      "product": "usa-virtual-accounts",
      "type": "individual"
    }
  },
  "response": {
    "status": 400,
    "headers": {
      "date": "Thu, 28 May 2026 02:26:40 GMT",
      "content-type": "application/json; charset=utf-8",
      "content-length": "158",
      "connection": "keep-alive",
      "x-amzn-requestid": "8f14ec9e-fd1b-4aa1-8df3-da50b19e8536",
      "x-dns-prefetch-control": "off",
      "referrer-policy": "no-referrer",
      "x-permitted-cross-domain-policies": "none",
      "x-xss-protection": "0",
      "strict-transport-security": "max-age=15552000; includeSubDomains",
      "x-amzn-remapped-content-length": "158",
      "x-frame-options": "SAMEORIGIN",
      "content-security-policy": "default-src 'self';base-uri 'self';font-src 'self' https: data:;form-action 'self';frame-ancestors 'self';img-src 'self' data:;object-src 'none';script-src 'self';script-src-attr 'none';style-src 'self' https: 'unsafe-inline';upgrade-insecure-requests",
      "origin-agent-cluster": "?1",
      "x-amzn-remapped-connection": "keep-alive",
      "cross-origin-opener-policy": "same-origin",
      "x-download-options": "noopen",
      "x-api-version": "2026-04-14",
      "x-amz-apigw-id": "eDcrEEBEPHcEdag=",
      "vary": "Origin",
      "x-content-type-options": "nosniff",
      "etag": "W/\"9e-iEcNeOcbiRzVlTRoic6qBUEcRkM\"",
      "cross-origin-resource-policy": "same-origin",
      "x-amzn-remapped-date": "Thu, 28 May 2026 02:26:40 GMT",
      "access-control-allow-credentials": "true",
      "cf-cache-status": "DYNAMIC",
      "set-cookie": "REDACTED(308)",
      "server": "cloudflare",
      "cf-ray": "a029d0d7e84db6ac-BOG"
    },
    "body": {
      "code": "validation_error",
      "error": "Invalid data",
      "details": [
        {
          "message": "type is Invalid enum value. Expected 'US_BANK' | 'MX_SPEI', received 'individual'"
        }
      ]
    }
  }
}